textgenerator/__init__.py
textgenerator/textgenerator_ai.py
textgenerator/utils.py
textgenerator_ai-1.0.0.dist-info/METADATA
textgenerator_ai-1.0.0.dist-info/WHEEL
textgenerator_ai-1.0.0.dist-info/top_level.txt
textgenerator_ai-1.0.0.dist-info/RECORD
