Metadata-Version: 2.4
Name: textgenerator_ai
Version: 1.0.0
Summary: Biblioteka w pythonie która służy do robienia czegoś podobnego do tqdm ale o wiele łatwiej.
Home-page: https://github.com/superbest14/generator
Author: Alexander
Author-email: alesiosawicki@gmail.com
License: MIT
Classifier: Programming Language :: Python :: 3
Classifier: Programming Language :: Python :: 3.7
Classifier: Programming Language :: Python :: 3.8
Classifier: License :: OSI Approved :: MIT License
Classifier: Operating System :: OS Independent
Classifier: Topic :: Software Development :: Libraries :: Python Modules
Requires-Python: >=3.7
